stylish_cmake_parser/__init__.py
stylish_cmake_parser/_version.py
stylish_cmake_parser/command.py
stylish_cmake_parser/command_group.py
stylish_cmake_parser/command_sequence.py
stylish_cmake_parser/element.py
stylish_cmake_parser/parse.py
stylish_cmake_parser/parser.py
stylish_cmake_parser/scanner.py
stylish_cmake_parser/section.py
stylish_cmake_parser-0.3.0.dist-info/METADATA
stylish_cmake_parser-0.3.0.dist-info/WHEEL
stylish_cmake_parser-0.3.0.dist-info/entry_points.txt
stylish_cmake_parser-0.3.0.dist-info/licenses/LICENSE
stylish_cmake_parser-0.3.0.dist-info/RECORD
